mpm_pytorch/__init__.py
mpm_pytorch/boundary_condition.py
mpm_pytorch/mpm_solver.py
mpm_pytorch/constitutive_models/__init__.py
mpm_pytorch/constitutive_models/abstract.py
mpm_pytorch/constitutive_models/elasticity.py
mpm_pytorch/constitutive_models/plasticity.py
mpm_pytorch/constitutive_models/warp_svd/__init__.py
mpm_pytorch/constitutive_models/warp_svd/svd.py
mpm_pytorch/constitutive_models/warp_svd/tape.py
mpm_pytorch-0.1.1.dist-info/LICENSE
mpm_pytorch-0.1.1.dist-info/METADATA
mpm_pytorch-0.1.1.dist-info/WHEEL
mpm_pytorch-0.1.1.dist-info/top_level.txt
mpm_pytorch-0.1.1.dist-info/RECORD
