Metadata-Version: 2.2
Name: mpm-pytorch
Version: 0.1.1
Summary: A PyTorch Implementation of MLS-MPM (Moving Least Squares Material Point Method)
Author-email: Yuchen Lin <yuchenlin0612@gmail.com>
Requires-Python: >=3.8
License-File: LICENSE
Requires-Dist: torch>=2.0.1
Requires-Dist: numpy<2
Requires-Dist: warp-lang==0.6.1
Requires-Dist: omegaconf
Requires-Dist: matplotlib
Requires-Dist: tqdm
